monitizer/__init__.py
monitizer/evaluate.py
monitizer/monitizer.py
monitizer/optimize.py
monitizer/parse.py
monitizer/benchmark/__init__.py
monitizer/benchmark/dataset.py
monitizer/benchmark/load.py
monitizer/benchmark/utils.py
monitizer/benchmark/datasets/__init__.py
monitizer/benchmark/datasets/datasets.py
monitizer/benchmark/datasets/generated_ood_dataloaders.py
monitizer/benchmark/datasets/CIFAR10/cifar10_dataloaders.py
monitizer/benchmark/datasets/CIFAR10/cifar10_dataset.py
monitizer/benchmark/datasets/CIFAR100/cifar100_dataloaders.py
monitizer/benchmark/datasets/CIFAR100/cifar100_dataset.py
monitizer/benchmark/datasets/DTD/dtd_dataloaders.py
monitizer/benchmark/datasets/DTD/dtd_dataset.py
monitizer/benchmark/datasets/FashionMNIST/fashionmnist_dataloaders.py
monitizer/benchmark/datasets/FashionMNIST/fashionmnist_dataset.py
monitizer/benchmark/datasets/GTSRB/gtsrb_dataloaders.py
monitizer/benchmark/datasets/GTSRB/gtsrb_dataset.py
monitizer/benchmark/datasets/Imagenet/imagenet_dataloaders.py
monitizer/benchmark/datasets/Imagenet/imagenet_dataset.py
monitizer/benchmark/datasets/KMNIST/kmnist_dataloaders.py
monitizer/benchmark/datasets/KMNIST/kmnist_dataset.py
monitizer/benchmark/datasets/MNIST/mnist_dataloaders.py
monitizer/benchmark/datasets/MNIST/mnist_dataset.py
monitizer/benchmark/datasets/SVHN/svhn_dataloaders.py
monitizer/benchmark/datasets/SVHN/svhn_dataset.py
monitizer/benchmark/generators/__init__.py
monitizer/benchmark/generators/distortiondatasets.py
monitizer/benchmark/generators/distortiontransformers.py
monitizer/benchmark/networks/cifar_10.py
monitizer/benchmark/networks/flatten.py
monitizer/monitors/ASHMonitor.py
monitizer/monitors/Bounds.py
monitizer/monitors/BoxMonitor.py
monitizer/monitors/DICEMonitor.py
monitizer/monitors/EnergyMonitor.py
monitizer/monitors/EntropyMonitor.py
monitizer/monitors/GaussMonitor.py
monitizer/monitors/GaussMonitorOneLayer.py
monitizer/monitors/GradNormMonitor.py
monitizer/monitors/KLMatchingMonitor.py
monitizer-0.0.1.dist-info/METADATA
monitizer-0.0.1.dist-info/WHEEL
monitizer-0.0.1.dist-info/entry_points.txt
monitizer-0.0.1.dist-info/top_level.txt
monitizer-0.0.1.dist-info/RECORD
