Metadata-Version: 2.4
Name: Monitizer
Version: 0.0.1
Summary: Monitizer is a tool to optimize and evaluate neural network monitors.
Author: Sudeep Kanav, Marta Grobelna, Muqsit Azeem, Sabine Rieder
Author-email: Stefanie Mohr <steffi.mohr@tum.de>
License: Apache License
Project-URL: Homepage, https://gitlab.com/live-lab/software/monitizer
Project-URL: Repository, https://gitlab.com/live-lab/software/monitizer
Project-URL: Documentation, https://monitizer.readthedocs.io
Keywords: neural network,monitor,ood,machine learning,optimization,evaluation
Classifier: Intended Audience :: Science/Research
Classifier: Intended Audience :: Developers
Classifier: License :: OSI Approved :: Apache Software License
Requires-Python: >=3.8
Requires-Dist: torch>=1.13.1
Requires-Dist: numpy>=1.21.6
Requires-Dist: pandas>=1.3.5
Requires-Dist: matplotlib>=3.5.3
Requires-Dist: scikit-learn>=1.0.2
Requires-Dist: onnx2pytorch>=0.4.1
Requires-Dist: plotly>=5.16.0
Requires-Dist: kaleido>=0.2.1
Requires-Dist: tqdm>=4.66.1
Requires-Dist: tabulate>=0.9.0
Requires-Dist: typing_extensions>=4.7.1
